kawaiired/__init__.py
kawaiired/aioclient.py
kawaiired/client.py
kawaiired/exceptions.py
kawaiired/utils.py
kawaiired-1.0.1.dist-info/METADATA
kawaiired-1.0.1.dist-info/WHEEL
kawaiired-1.0.1.dist-info/licenses/LICENSE
kawaiired-1.0.1.dist-info/RECORD
