Metadata-Version: 2.3
Name: kawaiired
Version: 1.0.1
Summary: A Python wrapper for the kawaii.red API.
Author-email: Keksi <contact@keksi.me>
License-File: LICENSE
Requires-Python: >=3.8
Requires-Dist: httpx>=0.27.0
